{"slug":"appressamento-della-morte","title":"Appressamento della morte","author":"Giacomo Leopardi","genre":"Poesia giovanile","source":"TXT caricato: appressa.zip","description":"Poema giovanile, diviso in canti.","sectionCount":5,"wordCount":6553,"sections":[{"title":"Canto I","text":"CANTO I\n\n\nEra morta la lampa in Occidente,\nE queto 'l fumo sopra i tetti e queta\nDe' cani era la voce e de la gente:\n\nQuand'i' volto a cercare eccelsa meta,\nMi ritrova' in mezzo a una gran landa,\nBella, che vinto è 'ngegno di poeta.\n\nSpandeva suo chiaror per ogni banda\nLa sorella del sole, e fea d'argento\nGli arbori ch'a quel loco eran ghirlanda.\n\nI rami folti gian cantando al vento,\nE 'l mesto rosignol che sempre piagne\nDiceva tra le frasche suo lamento.\n\nChiaro apparian da lungi le montagne,\nE 'l suon d'un ruscelletto che correa\nEmpiea il ciel di dolcezza e le campagne.\n\nFiorita tutta la piaggia ridea,\nE un'ombra vaga ne la valle bruna\nGiù d'una collinetta discendea.\n\nSprezzando ira di gente e di fortuna,\nPel muto calle i' gia da me diviso,\nCui vestia 'l lume della bianca luna.\n\nQuella vaghezza rimirando fiso,\nSentia l'auretta che gli odori spande,\nMollissima passarmi sopra 'l viso.\n\nSe lieto i' fossi è van che tu dimande,\nGrand'era 'l ben ch'aveva, ed era 'l bene\nOnde speme nutria, di quel più grande.\n\nAhi son fumo quaggiù l'ore serene!\nUn momento è letizia, e 'l pianto dura.\nAhi la tema è saggezza, error la spene.\n\nEcco imbrunir la notte, e farsi scura\nLa gran faccia del ciel ch'era sì bella,\nE la dolcezza in cor farsi paura.\n\nUn nugol torbo, padre di procella,\nSorgea di dietro ai monti e crescea tanto\nChe non si vedea più luna né stella.\n\nIo 'l mirava aggrandirsi d'ogni canto,\nE salir su per l'aria a poco a poco,\nE al ciel sopra mia testa farsi manto.\n\nVeniva 'l lume ad ora ad or più fioco,\nE 'ntanto tra le frasche crescea 'l vento,\nE sbatteva le piante del bel loco,\n\nE si facea più forte ogni momento\nCon tale uno stridor che svolazzava\nTra le fronde ogni augel per lo spavento.\n\nE la nube crescendo in giù calava\nVer la marina, sì che l'un suo lembo\nToccava i monti e l'altro il mar toccava.\n\nPareva 'l loco d'ombra muta in grembo\nDi notte senza lampa chiusa cella,\nE crescea 'l buio a lo 'ngrossar del nembo.\n\nGià cominciava 'l suon de la procella,\nE di lontan s'udiva urlar la pioggia\nCome lupi d'intorno a morta agnella.\n\nDentro le nubi in paurosa foggia\nGuizzavan lampi e mi fean batter gli occhi,\nE n'era 'l terren tristo e l'aria roggia.\n\nI' sentia già scrollarmisi i ginocchi\nCh'i tuoni brontolavano a quel metro\nChe torrente vicin che giù trabocchi.\n\nTalora i' mi sostava e l'aer tetro\nGuardava spaurato e poi correa\nSì ch'i panni e le chiome ivano addietro.\n\nE 'l duro vento col petto rompea\nChe gocce fredde giù per l'aria nera\nSoffiando, sopra 'l volto mi spignea.\n\nE 'l tuon veniami 'ncontra come fera\nRugghiando orribilmente senza posa,\nE cresceva la pioggia e la bufera.\n\nE ne la selva era terribil cosa\nIl volar foglie e rami e polve e sassi,\nE 'l rombar che la lingua dir non osa.\n\nI' non vedeva u' fossi ed u' m'andassi:\nTant'era pien di dotta e di terrore\nChe non sapea più star né mover passi.\n\nEra 'l balen sì spesso che 'l bagliore\nS'accendea sempre e mai non era spento,\nPerch' al fine i' ristetti a quell'orrore,\n\nE mi rivolsi indietro; e 'n quel momento\nSi stinse 'l lampo e tornò buja l'etra\nEd acquetossi 'l tuono e stette 'l vento.\n\nTaceva 'l tutto, ed i' era di pietra\nE sudava e tremava che la mente\nCome 'l rimembra, per l'orror s'arretra;\n\nE 'l palpitar si facea più frequente:\nQuando com'astro che per l'aer caggia,\nUn lume scese e femmisi presente.\n\nSplendeva in quella tenebria selvaggia\nSì chiaro che vincea vampa di foco,\nQual fornace di notte in muta piaggia,\n\nE splendendo cresceva a poco a poco;\nE 'n mezzo vi pareva uman sembiante\nVago sì ch'a 'l ritrar mio stile è roco.\n\nEd i' tremava dal capo a le piante,\nMa pur dolcezza mi sentia nel petto\nIn levar gli occhi a quel che m'era innante.\n\nBianco vestia lo Spirto benedetto\nRaggiante come d'Espero la stella,\nE avea 'l crin biondo e giovenil l'aspetto.\n\nIo l'Angel son che tua natura abbella,\nTua guardia, (e su i ginocchi allor cascai)\nCominciò quegli in sua santa favella.\n\nLa gran Signora da' sereni rai\nMandommi ch'ha di te pietade in cielo.\nPoco t'è lunge 'l dì che tu morrai.\n\nI' mi fei bianco in volto e venni gelo,\nAttonito rimasi e mi sentia\nRitrarsi 'l core ed arricciarsi 'l pelo.\n\nE muto stetti, e pur volea dir: Sia,\nO Signor, quel ch'è fermo in tuo consiglio,\nMa voce de la strozza non uscia.\n\nE sol potei chinar la fronte e 'l ciglio,\nE caddi al suol boccone; e quegli allora\nLevommi a un tratto e, Fa cor, disse, o figlio.\n\nNon ti dolga di tua poca dimora\nIn questa piaggia trista, e non ti caglia\nCh'ancor del quarto lustro non se' fora.\n\nOr ti parrà da quanto aspra battaglia\nVoler sia de l'Eterno che for esca,\nE come umana gente si travaglia,\n\nE quant'è van quel che le menti adesca,\nEd ammiranda vision vedrai,\nPer che gir di qua lunge non t'incresca,\n\nE poi soggiunse: Mira, ed i' mirai.","id":"canto-i"},{"title":"Canto Ii","text":"CANTO II\n\nParve di foco una vermiglia lista\nA l'orizzonte a galla sopra 'l mare,\nCh'atava in quell'orror la dubbia vista:\n\nCome di state dopo 'l nembo pare\nSul mar la notte luce di baleno\nChe lambe l'acqua e l'ombre fa più rare;\n\nO come ride striscia di sereno\nDopo la pioggia sopra la montagna,\nAllor che 'l turbo placasi e vien meno.\n\nEd i' vedeva gente molta e magna\nPassar non lunge innanzi a quel chiarore,\nChe n'era piena tutta la campagna.\n\nE primier vidi sogghignando Amore\nSvolazzar su la gente di suo regno\nTanta ch'e' di quaggiù parea signore.\n\nIva misera turba che fu segno\nA suoi strali roventi, e parea tutta\nAtteggiata di doglia e di disdegno.\n\nQuesti son que' che ne la fera lutta\nDi nostra vita vinse la gran possa\nDi quel desio che pianto e morte frutta.\n\nQuest'è la turba che nel mondo ingrossa\nAl volger d'ogn'istante, e non vien manco\nPer volar d'ora o spalancar di fossa.\n\nFermo i' guardava, e quel che m'era al fianco\n(E 'l potea ben senza mirarmi in viso)\nScorse il dubbiar de lo 'ntelletto stanco.\n\nE disse: Questa è gente che di riso\nNon ebbe un'ora in vostra vita lassa,\nPur sempre ebbe a cercarlo il pensier fiso.\n\nE nutrì speme pazza e voglia bassa,\nLocando suo desire in cosa vana,\nEd amò ben che quando giugne, passa.\n\nQuel vergognoso là che s'allontana,\nÈ 'l Prence tristo per lo cui delitto\nTant'alta venne la virtù Romana.\n\nAppio è quel là che conto a voi fe' 'l dritto,\nPel cui malvagio amore un'altra volta\nRoma fu lieta e suo tiranno afflitto.\n\nAntonio è quel che lamentar s'ascolta,\nE di suo fato no ma par si lagne\nSol che sua donna scaltra gli sia tolta.\n\nVedi Parisse più vicin che piange\nIlio in faville e la reggia diserta\nE morti i frati e serve le compagne\n\nE d'erba e sassi la città coverta:\nE fu cagion di tanta doglia Amore.\nE vedi quel ch'ha sì gran piaga aperta.\n\nÈ Turno, e per Lavinia è 'l suo dolore,\nPer chi di morti fe' sì gran catasta\nQuel ch'al Tebro menò le Teucre prore.\n\nVedi Sanson colà che mal contrasta\nA Dalila, e 'l gran Re ch'anco si dole\nChe sapienza contr'Amor non basta.\n\nMira quell'alme quivi che van sole\nCon la faccia scarnata e 'l ciglio basso,\nE movon lente e senza far parole.\n\nVestali furo, e sotto flebil sasso\nMenolle dura legge e crudo foco\nDi per loro a compor lo corpo lasso.\n\nVedi quanti ha malconci 'l tristo gioco,\nE perduti ha 'l furor di voglia insana,\nChe tempo lungo a noverargli è poco.\n\nGuata quel truce là ch'a la Cristiana\nFede aprì 'l lato, e che nel suol Britanno\nDi giusto sangue fe' tanta fontana,\n\nE per Amor, di Re venne tiranno,\nE mandò giù tant'alme a l'aria bruna,\nSì ch'ancor dura e sarà eterno 'l danno;\n\nPer chi d'Anglia tal frotta si rauna\nE mugolando s'addossa e si preme\nQual sozzo gregge a la 'nfernal laguna.\n\nD'infinita sciaura Amor fu seme,\nChe non sua sol ma van mill'alme ognora\nPer lui 've 'l tristo eternamente freme.\n\nOh miser'Anglia che tanta dimora\nFai ne l'Errore, e non ti basta 'l lume\nDe la mental tua lampa a uscirne fora,\n\nE già tutto conosci forchè 'l Nume,\nE cieco nasce e non vi pensa e more\nTuo popol gramo vinto dal costume.\n\nPoi sospirando disse: Or vedi, Amore\nCom'è crudele al mondo, e com'è duro\nFar ch'e' non giunga a palpeggiarti 'l core.\n\nSapienza non è sì saldo muro\nChe nol dirompa forza di suo strale,\nE chi men l'ha provato è men sicuro.\n\nE se l'alma infermò di tanto male\nE sente l'aspra punta, ov'è la pace?\nE se pace non è, viver che vale?\n\nSì come chi per poi soggiunger tace,\nQuel tacque, ed i' mi vidi un mesto avante\nGiovane e tal che d'ello anco mi spiace.\n\nTanto mi vinse suo flebil sembiante\nChe l'Angel di suo nome interrogai,\nBenchè mio dir sonava ancor tremante.\n\nE quel rispose: Da sua bocca udrai\nContar suo fallo e di suo fallo i danni.\nE l'approcciammo, ed i' l'addimandai.\n\nUgo fui detto, e caddi in miei verd'anni,\nE me Ferrara tra suoi forti avria,\nSe non fosse 'l mio padre infra' tiranni,\n\nDisse e ristette e quasi si pentia,\nPoi seguitò: Mi trasse al punto estremo\nNon so se di mio fato o colpa mia.\n\nI' membro l'ora, ed in membrarla fremo,\nChe prima vidi le sembianze ladre\nPer ch'in eterno fra quest'alme gemo.\n\nVidi la donna misera che 'l padre\nErasi aggiunta, ma che 'l tristo letto\nnon fe' bello di prole e non fu madre.\n\nE cura inquieta mi sentii nel petto\nChe parea dolce, ma la voglia rea\nVanezza e tedio femmi ogni diletto.\n\nIo fea contesa e forse ch'i' vincea,\nMa un dì fui sol con quella in muto loco,\nE bramava ir lontano e non volea,\n\nE palpitava, e 'l volto era di foco,\nE al fine un punto fu che 'l cor non resse,\nTanto ch'i' dissi: t'amo, e 'l dir fu roco.\n\nVergogna allor sul ciglio mi s'impresse,\nE la donna arrossar vidi e gir via\nSenza far motto, come lo sapesse.\n\nPoi nulla i' fei, ma tanto più che pria\nDivampò 'l foco al soffio di speranza,\nCh'arder le vene e i polsi i' mi sentia.\n\nAllor che tratto di mia queta stanza\nFui d'armato drappello in su la sera\nCon ferità ch'ogni mio dire avanza,\n\nE dentro muta torre in prigion nera\nChiuso che 'ndarno il genitor chiamava,\nImmobil tra catene come fera.\n\nStupido e sol rimasi in quella cava\nRicercando mia colpa, ed oh dolore\nIn ricordarmi di mia voglia prava!\n\nEra giunta la notte a le tard'ore\nChe tace e per le vie gente non passa,\nQuando fioco romor sentii di fore.\n\n(O Italia mia dolente, o patria lassa\nChe quant'alta a' bei giorni tanto cruda\nFosti a' più neri, e tanto ora se' bassa,\n\nBen sei di luce muta e d'onor nuda,\nChe tigre fosti quando era tua possa,\nE or se' pietosa ch'uom per te non suda!)\n\nOrrendo un gel mi sdrucciolò per l'ossa,\nE mancar sentii 'l fiato e 'l cor serrarse\nQuand'a l'uscio udii dar la prima scossa.\n\nSonaro i ferri al suo dischiavacciarse,\nE seguì di persona un calpestio,\nE di lontana fiamma un chiaror parse.\n\nCome chi vide 'l lampo che fuggio,\nAspetta lo fragore e sta sospeso,\nTal senza batter ciglio mi stett'io.\n\nE 'l genitore entrar che tenea steso\nIl destro braccio e ne la man mirai\nUn ferro e 'n la sinistra un torchio acceso.\n\nMorta è, disse, tua druda e tu morrai.\nSu le ginocchia i' caddi in quel momento:\nPiagneva e volea dir: mio padre, errai.\n\nMa la punta a mia gola e' ficcò drento,\nE caddi con la bocca in su rivolta,\nE 'l vital foco tutto non fu spento.\n\nParvemi che l'acciaro un'altra volta\nAlzasse, e di vibrarlo stesse in forse;\nPoscia com'uom che di lontano ascolta,\n\nL'udii cercar de l'uscio: indi ritorse\nIl passo, e 'n cor piantommi e lasciò 'l brando,\nPerchè l'ultimo ghiaccio là mi corse.\n\nE svolazzò lo spirto sospirando.","id":"canto-ii"},{"title":"Canto Iii","text":"CANTO III\n\nI' lagrimava già per la pietate\nDi quella miser'alma che perduta\nAvea suo fallo e altrui crudelitate,\n\nE 'l ciglio basso e la bocca era muta,\nQuando 'l Celeste, Guata là quel duce,\nDisse, ch'ha man grifagna ed unghia acuta.\n\nÈ l'Avarizia, e dietro si conduce\nGregge che 'n vita fu de l'oro amico\nNon perchè val tra voi ma perchè luce.\n\nDel nome di que' duri io non ti dico,\nChe non sudar perchè 'l sapesse 'l mondo\nQuando lor tempo avria chiamato antico.\n\nVe' ch' han sul collo di gran soma pondo,\nE van carpone e 'l capo in giù pendente,\nSì che lor faccia è presso d'ogn'immondo,\n\nPerò che prona al suolo ebber la mente,\nE di gloria e del ciel non ebber cura,\nVivendo in terra come morta gente.\n\nOr vedi quanto è trista e quanto è dura\nVostra vita mortal, che 'l fango e 'l fimo\nPiù che la gloria e 'l ciel per voi si cura.\n\nBen sete fatti di terrestre limo,\nChe tanta gente cerca morta terra,\nPer lo suo fine e per l'autor suo primo.\n\nE pur bell'alma vostro corpo serra\nPerchè ricerchi e trovi 'l sommo Amore,\nChe pace è vostro fin, non questa guerra.\n\nQui tacque, e venne pallido 'l chiarore,\nCh'iva aliando fosca tenebria\nCome nottola oscena, in quell'orrore.\n\nVenia Gigante altissimo, e 'l seguia\nLunghissim'ombra piena di spavento,\nCieco così che brancolando gia.\n\nCorrea da prima ratto come vento,\nPoi tenne 'l passo per lo buio calle,\nSì ch'iva al fine come neve lento.\n\nGli era infinito esercito a le spalle,\nE di voci facea tanto certame\nChe tutta piena d'eco era la valle.\n\nIvan latrando quelle genti grame,\nE su lor crespa fronte e su la cava\nLor mascella parea seder la fame.\n\nAl lume i' gli scorgea che s'avventava\nDa le Angeliche forme ai visi smorti,\nE men chiaro e più fioco ritornava.\n\nQuesti tenner sentieri oscuri e torti\nIn cercar verità, lo Spirto disse,\nD'errar volenterosi, o malaccorti.\n\nVedi colui che così presto visse,\nZoroastro inventor di scienza vana,\nE quel che 'nsegnò tanto e nulla scrisse:\n\nI' dico 'l Samio mastro che l'umana\nMente fe' vil così che la ridusse\nA starsi con le fere in bosco e 'n tana:\n\nE quel da Citte che tanta produsse\nGente al dolor sì come al piacer dura,\nE l'Abderita che la mente strusse,\n\nE la Cinica turba che sicura\nDa error non fu sotto 'l cencioso panno,\nE 'l lercio duce de la mandra impura.\n\nVe' come soli e pensierosi vanno\nSocrate e Plato e 'l magno di Stagira,\nSdegnando 'l gregge e lo comun tiranno.\n\nGuata là que' nefandi pieni d'ira\nContra l'Eterno, sopra la cui testa\nSolcato da baleni un turbo gira.\n\nE sentigli ulular come foresta\nAllor che 'nfuria 'l vento, e che rimbomba\nPer l'aer fosco voce di tempesta.\n\nOh quanta gente è qui che ne la tomba\nNon è fatta anco polve, oh quanta gente\nAl disperato lago or tra lei piomba!\n\nCome brulica giù l'onda bollente\nPer color cui fe' vano il grande acquisto\nSpietato inganno di corrotta mente!\n\nOh menti sciagurate, oh mondo tristo\nCui lo pensier del vero tanto spiace\nChe par vergogna il ragionar di Cristo!\n\nGià contra 'l ciel latrava, ed or si tace\nTua gente in guisa d'uom che non si cura,\nCome a Dio conceduta abbia la pace.\n\nVedi, soggiunse, o figlio, com'è scura\nVostra terrena via piena di doglia,\nE com'è fral quaggiù vostra natura.\n\nChe tanta gente di seguir s'invoglia\nQuel Gigante colà ch'è 'l tristo Errore,\nE tanta ignara il fa contra sua voglia.\n\nQuanti cercar saggezza e saldo onore\nChe trovar fama tetra e falsitate,\nE lor fu vano il trapassar de l'ore!\n\nOh savissime sole oh avventurate\nL'alme che ricercar del sommo Bene!\nFumo già non trovar né vanitate.\n\nDier soda meta a lor non dubbia spene,\nBramando uscir di questa terra bassa\nU' torpe Error che così presto viene.\n\nPerò 'l Gigante che tant'ombra lassa\nSopra 'l dolente esercito seguace,\nVenne sì ratto e così lento passa.\n\nGià la piaggia parea tornare in pace\nPel lontanar di quella turba folta\nSopra cui 'l lume eternamente tace.\n\nDa lungi la s'udia come talvolta\nDi nembo cui sul mar lo vento caccia,\nL'urlar tra l'onde e 'l mormorar s'ascolta;\n\nO notturna del mar cupa minaccia\nPerchè' l villan che presso il turbo crede\nSi desta e sorge ed al balcon s'affaccia.\n\nAllor ch'a un tratto sì come si vede\nCampo di secche canne incontr'al sole,\nQuand'e' co' rossi raggi a sera il fiede;\n\nO come andar tra noi di faci suole\nNotturno stuol, di Cristo appo 'l feretro,\nIl dì che di sua morte il ciel si dole:\n\nCotal si vide in mezzo a l'aer tetro\nUn lampeggiar di scudi e lance e spade\nChe tremolava intorno a fero spetro.\n\nSua scossa asta parea grandin che cade\nCon alto rombo giù da nugol nero\nSu i tetti rimbalzando e per le strade.\n\nTentennava sua testa atro cimiero,\nE pendea 'l brando nudo in rossa lista,\nDigocciolando sangue in sul sentiero.\n\nIva 'l membruto mostro e facea trista\nTutta sua via, che dietro si lasciava\nFoco ch'ardea tra l'erbe in fera vista.\n\nVe', l'Angel disse, la crudel che lava\nCol sangue i campi, e col brando rovente\nFa tante piaghe e tante fosse scava.\n\nAltro costume de l'umana gente:\nCacciar lo ferro gelido e la mano\nDel prossimo nel corpo e del parente:\n\nCorrere e disertar lo monte e 'l piano,\nE 'n un giorno e 'n un punto l'opra e 'l frutto\nDi sudor molto e molta età far vano:\n\nStrugger mura, arder tempi e farsi brutto\nDi cenere e vestirsi di terrore,\nE 'ngoiar le cittadi come flutto:\n\nGuastar campagne e al pavido cultore\nMessa la man tra le sudate chiome,\nDi sua casuccia strascinarlo fore:\n\nBrillar tra morti e 'nsanguinati come\nLion che 'n belva marcida si sfama;\nRider tra genti lagrimose e dome.\n\nDunque far solo il mondo è vostra brama,\nE 'l viver vostro è per l'altrui morire,\nE sì tra voi si viene in seggio e 'n fama?\n\nVe' di quegli aspri le sembianze dire\nLo cui passaggio al mondo fu guadagno,\nE 'l natale e la vita fu martire.\n\nMira colui che nome ebbe di Magno,\nE fe' di sangue Egizia frode rossa;\nE 'l Pelide che piange suo compagno,\n\nE Guerra maladice e la sua possa,\nE presso ha 'l re de' re che 'l Teucro lido\nCopre di spoglie sanguinose e d'ossa,\n\nE vincitor perì di ferro infido,\nE per Guerra perdè la luce e 'l regno;\nE quel che 'nvan divenne a tanto grido:\n\nIl Macedone i' dico, ch'ha disdegno\nPerò ch'ir vana da la morta valle\nDi sua man l'opra vide e di suo 'ngegno:\n\nE Ciro e Brenno e Pirro ed Anniballe\nChe grandi un tempo e fur meschini allora\nChe fortuna lor dato ebbe le spalle;\n\nE come Sol per nembo si scolora,\nVider lor fama intenebrarsi, e poi\nVenir pallida e muta l'ultim'ora.\n\nCosì passa fortuna degli Eroi,\nE la gran mole in un sol dì fracassa\nChe tanto pianto fe' versar tra voi:\n\nCom'onda a gli astri sorta che s'abbassa\nE cade in un baleno e al pian s'agguaglia,\nE di suo levamento orma non lassa.\n\nTacque, e cadeva 'l suon de la battaglia\nChe giva di colei per lo sentiero\nChe tutto 'l mondo misero travaglia.\n\nE mostro altro pareva onde più fero\nNon vede orma stampar su neve o sabbia\nLo Scita algente o 'l divampato Nero.\n\nAveva umane forme e umana labbia,\nE passeggiar parean la guancia scura\nL'invidia fredda e la rovente rabbia,\n\nE a suo passaggio abbrividir natura,\nSeccarsi l'erbe, e tremolar le piante\nScrollando i rami come per paura.\n\nNel buio viso l'occhio fiammeggiante,\nA carbon tra la cenere, che splenda\nSolingo in cieca stanza, era sembiante.\n\nAl crin gli s'attorcea gemmata benda,\nE scendea regio manto da le spalle\nCom'acqua bruna che di rupe scenda.\n\nSprizzato era di sangue, e per lo calle\nDi sangue un lago fea la sozza vesta,\nChe in dubbia e torta striscia iva a la valle.\n\nSeguialo incerto rombo di tempesta,\nEd egl'iva sospeso, e ogni momento\nIl serto si cercava ne la testa.\n\nParea pien di sospetto e di spavento,\nGuardavasi d'intorno, e tenea 'l passo\nAl suon de' rami e al transito del vento.\n\nEcco 'l gran vermo d'uman sangue grasso,\nLo qual però che 'l mondo ha 'n sua balia,\nBen si conviene andar col ciglio basso.\n\nEcco 'l figliol di vostra codardia,\nCominciò quegli, ecco la belva lorda,\nEcco la perfid', ecco Tirannia.\n\nQuella che sempre vora e sempre è 'ngorda\nQuella ch'è cieca come marmo al pianto,\nQuella ch'è al prego come bronzo sorda.\n\nO mondo gramo e se' codardo tanto\nCh'uom su tuo' seggi può seder sicuro\nDi sangue intriso la corona e 'l manto?\n\nE quando etade ha suo passar maturo,\nPassa 'l tiran già sazio, e allor pur anco\nTrovar chi 'l biasmi e chi l'accusi è duro?\n\nE di soffrir quest'orsa non se' stanco\nChe ti ficca e rificca l'unghia e 'l dente\nNel rosso petto e 'n lo squarciato fianco?\n\nOh sciagurato mondo, oh età dolente,\nOh progenie d'Abisso atri tiranni,\nOh infamia eterna de l'umana gente!\n\nQuest'è la bestia che da' tuoi verd'anni\nT'arse di rabbia, e del cui lercio sangue\nTinta bramasti aver la mano e i panni.\n\nQuest'è l'orribil idra, quest'è l'angue\nChe gonfia sopra 'l mondo alza la cresta,\nPerchè virtude è morta e 'l saper langue.\n\nVedi come la piaggia si fa mesta\nAl passar de la fera, e ve' 'l pugnale\nCh'ha per iscettro, e 'l sangue che calpesta.\n\nVedi 'l nefando stuol che fu mortale\nA lo sgraziato mondo, e da cui 'l mondo\nNon ebbe che 'l campasse brando o strale.\n\nVedi Tiberio là, vedi l'immondo\nGregge di que' che ne l'età più nera\nItalia tua gravar di tanto pondo.\n\nVe' 'l furbo più vicin che spinse a sera\nLa libertà Romana, e n'ebbe fama,\nE ancor d'amici al mondo ha tanta schiera.\n\nVe' Periandro lo tristo che brama\nTenne d'aver tra' greci saggi onore,\nE sua Corinto misera fe' grama.\n\nPur ve' che di vergogna e di furore\nArse talor la gente, ed avventosse\nCol ferro nudo del tiranno al core.\n\nAllora Armodio vidi ch'avea rosse\nLe man de l'empio sangue, e per man rea\nCadde, e per fama a un punto rilevosse.\n\nE 'l gran Corintio vidi che piangea\nSul prosteso fratel che venia manco\nPel colpo onde suo brando lo spegnea.\n\nE Bruto del tiranno aprir lo fianco,\nE del Romano Imperador primiero\nSquarciato 'l petto vidi e 'l volto bianco.\n\nI' tenea 'l guardo fiso ed il pensiero\nA quella truce vista, allor che sparse\nOgni chiarore, e 'l ciel si fe' più nero.\n\nE 'n un momento 'l vidi spalancarse:\nUscinne un tuono, e un fulmine strisciosse\nPer l'etra, e su la fera cadde e l'arse,\n\nE misto di faville un fumo alzosse.","id":"canto-iii"},{"title":"Canto Iv","text":"CANTO IV\n\nTornò la piaggia queta: allor che sopra\nOscuro carro apparse un che si stava\nImmoto in guisa d'uom cui sonno copra.\n\nSedeva, e sopra 'l petto gli cascava\nLa testa ciondolante, e 'l carro gia\nCome va carro cui gran pondo grava.\n\nTestuggini 'l traeano, e per la via\nMoveasi taciturno e così lento\nChe suon di rota o sasso non s'udia.\n\nVedi, 'l Celeste disse, quel ch'ha spento\nLa fama e 'l grido di que' magni tanti\nLo cui rinomo è gito come vento.\n\nVedi che 'ntorno al carro e dietro e innanti\nVa quella gente trista lo cui volto\nTutto è 'nvoluto entro suoi lunghi manti.\n\nQuesta die' tempo lungo e sudor molto\nPer viver dopo 'l passo, e tutto 'l frutto\nDe l'opra sua quel suo signor gli ha tolto.\n\nOr muto di suo nome è 'l mondo tutto:\nPur die' la vita perch'eterno fosse,\nE 'l mertava quant'altri, e que' l'ha strutto.\n\nO sventurata gente, e che ti mosse\nA ricercar quel che da Obblio si fura,\nSì che giace tua fama entro tue fosse?\n\nOh vita trista, oh miseranda cura!\nPassa la vita e vien la cura manco,\nE 'l frutto insiem con lor passa e non dura.\n\nQuando posasti il moribondo fianco,\nDicesti: Assai vivemmo, e non fia mai\nChe nostro nome di sonar sia stanco.\n\nMisera gente, ah non vivesti assai\nPer trionfar d'Obblio che tutto doma:\nInvan per te vivesti e non vivrai.\n\nQuanto me' fa colui che non si noma\nAl mondo no, ma nomerassi in cielo\nQuando deposto avrà la mortal soma.\n\nLui dolcezza sarà lo final gelo,\nNè teme Obblio, ch'avrà la terra a sdegno\nQuando vedrà 'l gran Bello senza velo.\n\nOr ti rafforza, o mio povero 'ngegno,\nE t'aiti colui che tutto move\nChe dir t'è d'uopo di suo santo regno.\n\nOr prendi a far quaggiù l'ultime prove,\nOra a mia bocca ispira il canto estremo.\nCose altissime canto al mondo nove.\n\nVe', quel soggiunse, e 'n ripensarvi io tremo,\nChe solcando si va questo mar tristo\nCon iscommessa barca e fragil remo.\n\nAssai travaglio assai dolore hai visto:\nOr leva 'l guardo a le superne cose,\nOr mira 'l frutto del divino acquisto.\n\nI' sollevai le luci paurose\nInver lo cielo, e vidi quel ch'appena\nMie voci smorte di ridir son ose.\n\nCome quando improvviso si serena\nIl ciel già fosco sopra piaggia bella,\nE 'l sol ridendo torna e 'l dì rimena,\n\nE 'l loco sua letizia rinnovella\nMentre in ogn'altra parte è 'l ciel più nero\nE tutto intorno chiuso da procella:\n\nCosì lassuso in mezzo a l'emispero\nFendersi vidi i nugoli e squarciarse,\nE disfogando i rai farsi sentiero.\n\nE poi l'aperta vidi dilatarse,\nE crescer lo splendore a poco a poco,\nSì che lucido campo in cielo apparse.\n\nLume di Sole a petto a quello è fioco\nChe rifletteasi 'n terra e 'l suol fea vago\nBrillando tra le foglie del bel loco,\n\nQual da limpido ciel su queto lago\nCinto di piante in ermo loco il Sole\nVersa sua luce e sua tranquilla imago.\n\nQui vengon manco al ver le mie parole,\nCh'i' vidi cose in mezzo a quel fulgore,\nCui dir non può la lingua, e 'l pensier vole.\nVidi distesa piaggia onde 'l colore\nE 'l fiorire e 'l gioire e la beltate\nM'aprir la mente e dilatarmi 'l core.\n\nCanti s'udian sì dolci che di state\nMen caro è sul meriggio in riva a un fiume\nUdir gli augelli e l'aure innamorate.\n\nSplendean l'erbette di sì vago lume\nChe luccicar men vaghi a la mattina\nI rugiadosi prati han per costume.\n\nE la luce era tanta che la brina\nAl Sol men chiaro splende, e men raggiante\nSplende al Sol bianca neve in piaggia alpina.\n\nIntrecciavansi i raggi tra le piante,\nE rifletteansi in onde tanto chiare\nChe quel fulgor quaggiù non ha sembiante.\n\nCome se viva lampa a un tratto appare\nIn tenebrosa stanza, chi v'è drento\nForz'è che 'l lume con la man ripare:\n\nSì mi vinser que' raggi in un momento:\nPerchè l'umide luci i' riserrai,\nChe 'l poter venne manco a l'ardimento.\n\nE l'Angel disse: mira, ed i' levai\nLo sguardo un'altra volta, e vidi quanto\nNostra sola virtù non vide mai.\n\nAlme vestite di lucido manto\nIvan per quelle vie del Paradiso,\nSciolte le labbra al sempiterno canto.\n\nOh che soavi lumi, oh che bel viso,\nOh che dolci atti in quel beato stuolo,\nOh che voci, oh che gioia, oh che sorriso!\n\nAllor mi parve abbandonato e solo\nQuesto misero mondo, e 'l dolor molto\nE 'l piacer nullo in questo basso suolo.\n\nPiù ch'astro fiammeggiante era lor volto,\nE 'n guisa d'uom che placido si bea,\nE' 'l tenean fermo e tutto in su rivolto.\n\nS'allegrava 'l terren quando 'l premea\nAlcun de' Santi con l'eterno piede,\nE ogn'erba da lor tocca più lucea.\n\nMira de' Giusti la beata sede,\nMira la patria, mira 'l sommo regno\nCui non cura 'l mortal perchè nol vede.\n\nOr sì lo tristo suol verratti a sdegno,\nDisse 'l Celeste, or sì ti saria duro\nDrizzar la mente a men beato segno.\n\nO 'ntelletto mortal, come se' scuro,\nChe cerchi morte e duol, per questa terra\nChe da doglia e da morte fa sicuro!\n\nVedi color che 'l santo loco serra\nCom' or son lieti ne l'eterna pace,\nVinta presto quaggiù la mortal guerra.\n\nMira 'l vate regal che sì ferace\nEbbe di canti sua divina cetra,\nE tra gli altri lassuso or già non tace.\n\nVedi 'l magno Alighier che sopra l'etra\nRicordasi ch'ascese un'altra volta,\nE del dir vostro pose la gran pietra.\n\nE vedi quel vicin ch'anco s'ascolta\nLagnarsi che la mente al mondo tristo\nEbbe a cosa mortal troppo rivolta.\n\nMira colui che lagrimar fu visto\nTutta sua vita, e or di suo pianto ha 'l frutto,\nE cantò l'armi e 'l glorioso acquisto.\n\nOh dolce pianto, oh fortunato lutto,\nOh vento che 'l nocchier sospinse al porto\nU' nol conturba più vento nè flutto!\n\nI' stava in quella vista tutto assorto\nQuando repente correr come strale\nUn lampo vidi da l'occaso a l'orto.\n\nAllor per l'aria tutta batter l'ale\nRugghiando i quattro venti, e 'l tuon mugghiare\nDal boreal deserto al polo australe,\n\nE sbattersi da lungi e dicrollare\nLor cime i monti, e dal profondo seno\nMetter continuo cupo ululo il mare,\n\nE l'aria farsi roggia in un baleno\nCome le nubi a sera in occidente,\nE sotto a' piedi ansando ir lo terreno,\n\nE 'l ruscel che venuto era torrente,\nSpumar fumar con alto gorgoglìo\nSì come in vaso al foco onda bollente.\n\nQuando con suon vastissimo s'aprio\nIn mezzo al santo loco il ciel più addrento,\nE allor cademmo al suol l'Angelo ed io.\n\nE tra sua luce sopra 'l firmamento\nApparve Cristo e avea la Madre al fianco,\nE tutto tacque e stette in quel momento.\n\nCosì smarrissi lo 'ntelletto stanco\nQuando l'Angel mi fe' levar lo viso,\nChe 'n lo membrar la voce e 'l cor vien manco.\n\nVidi Cristo, e non sono in Paradiso?\nE Maria vidi, e 'n terra anco mi veggio?\nE vidi 'l cielo, e altrui pur lo diviso?\n\nO Cristo, o Madre, o sempiterno seggio\nU' celeste si fa nostra natura,\nChe narrar di voi posso e che dir deggio?\n\nT'allegra omai, che tua stagion matura,\nDisse lo Spirto, e sei presso a la sede\nOve letizia eternamente dura.\n\nCristo e la Madre vede, e sol non vede\nTuo mortal guardo quel che veder mai\nNon può da questo mondo altro che fede.\n\nQuella nube tel cela da' cui rai\nLo fiammeggiar di cento Soli è vinto,\nDove pur di mirar forza non hai.\n\nDico la somma Essenza inver cui spinto\nÈ dal cor suo ma ch'a mirar non basta\nUom da suo corpo a questa terra avvinto.\n\nConto t'è 'l mondo omai, conta la vasta\nSolitudin terrena ov'uomo ad uomo\nEd a se stesso ed a suo ben contrasta.\n\nVedesti i frutti del piagnevol pomo,\nE 'l cercar gioia che 'n dolor si muta,\nE le vane speranze e 'l van rinomo:\n\nCome dietro ad Error sen va perduta\nTanta misera gente, e come tanti\nVisser per Fama di cui Fama è muta.\n\nVedesti i feri guai vedesti i pianti\nChe reca armato chi ragion non prezza,\nE i crudi giochi e i luttuosi vanti.\n\nChe far nel mondo vostro dove spezza\nSue leggi e suo dover lo rege ei pure,\nE misero diviene in tant'altezza,\n\nSe non cercar del cielo ove sicure\nSon l'alme dal furor de la tempesta,\nE tema è morta e le roventi cure?\n\nE lo ciel ti si dona. Omai t'appresta,\nChe veduto non hai sogni nè larve:\nCerta e verace vision fu questa.\n\nPresso è 'l dì che morrai. Qui tutto sparve.","id":"canto-iv"},{"title":"Canto V","text":"CANTO V\n\nDunque morir bisogna, e ancor non vidi\nVenti volte gravar neve 'l mio tetto,\nVenti rifar le rondinelle i nidi?\n\nSento che va languendo entro mio petto\nLa vital fiamma, e 'ntorno guardo, e al mondo\nSol per me veggo il funeral mio letto.\n\nE sento del pensier l'immenso pondo,\nSì che vo 'l labbro muto e 'l viso smorto,\nE quasi mio dolor più non ascondo.\n\nPoco andare ha mio corpo ad esser morto.\nI' mi rivolgo indietro e guardo e piagno\nIn veder che mio giorno fu sì corto.\n\nE 'n mirar questo misero compagno\nCui mancò tempo sì ch'appien non crebbe,\nDico: misero nacqui, e ben mi lagno.\n\nTrista è la vita, so, morir si debbe;\nMa men tristo è 'l morire a cui la vita\nChe ben conosce, u' spesso pianse, increbbe.\n\nI' piango or primamente in su l'uscita\nDi questa mortal piaggia, che mia via\nOve l'altrui comincia ivi è finita.\n\nI' piango adesso, e mai non piansi pria:\nSperai ben quel che gioventude spera,\nQuel desiai che gioventù desia.\n\nNon vidi come speme cada e pera,\nE 'l desio resti e mai non venga pieno,\nCosì che lasso cor giunga la sera.\n\nSeppi, non vidi, e per saper, nel seno\nNon si stingue la speme e non s'acqueta,\nE 'l desir non si placa e non vien meno.\n\nArdea come fiammella chiara e lieta,\nMia speme in cor pasciuta dal desio\nQuando di mio sentier vidi la meta.\n\nAllora un lampo la notte m'aprio,\nE tutto cader vidi, allor piagnendo\nAi miei dolci pensieri i' dissi: addio.\n\nGià l'avvenir guardava, e sorridendo\nDicea: Lucida fama al mondo dura,\nFama quaggiù sol cerco e fama attendo.\n\nMisero 'ngegno non mi die' natura.\nAnco fanciullo son: mie forze sento:\nA volo andrò battendo ala sicura.\n\nSon vate: i' salgo e 'nver lo ciel m'avvento,\nArdo fremo desio sento la viva\nFiamma d'Apollo e 'l sopruman talento.\n\nGrande fia che mi dica e che mi scriva\nItalia e 'l mondo, e non vedrò mia fama\nTacer col corpo da la morta riva.\n\nSento ch'ad alte imprese il cor mi chiama.\nA morir non son nato, eterno sono\nChe 'ndarno 'l core eternità non brama.\n\nMentre 'nvan mi lusingo e 'nvan ragiono,\nTutto dispare, e mi vien morte innante,\nE mi lascia mia speme in abbandono.\n\nAhi mio nome morrà. Sì come infante\nChe parlato non abbia i' vedrò sera,\nE mia morte al natal sarà sembiante.\n\nSarò com'un de la volgare schiera,\nE morrò come mai non fossi nato,\nNè saprà 'l mondo che nel mondo io m'era.\n\nOh durissima legge, oh crudo fato!\nQui piango e vegno men, che saprei morte,\nObblivion non so vedermi allato.\n\nViver cercai quaggiù d'età più forte,\nE pero e 'ncontr' a Obblio non ho più scampo,\nE cedo, e me trionfa ira di sorte.\n\nMorir quand'anco in terra orma non stampo?\nNè di me lascerò vestigio al mondo\nMaggior ch'in acqua soffio, in aria lampo?\n\nChe non scesi bambin giù nel profondo?\nE a che se tutto di qua suso ir deggio,\nFu lo materno sen di me fecondo?\n\nEterno Dio, per te son nato, il veggio,\nChe non è per quaggiù lo spirto mio,\nPer te son nato e per l'eterno seggio.\nDeh tu rivolgi lo basso desio\nInver lo santo regno inver lo porto.\nO dolci studi o care muse, addio.\n\nAddio speranze, addio vago conforto\nDel poco viver mio che già trapassa:\nItene ad altri pur com'i' sia morto.\n\nE tu pur, Gloria, addio, che già s'abbassa\nMio tenebroso giorno e cade omai,\nE mia vita sul mondo ombra non lassa.\n\nPer te pensoso e muto alsi e sudai,\nE te cerca avrei sempre al mondo sola,\nPur non t'ebbi quaggiù nè t'avrò mai.\n\nPovera cetra mia, già mi t'invola\nLa man fredda di morte, e tra le dita\nLo suon mi tronca e 'n bocca la parola.\n\nPresto spira tuo suon, presto mia vita:\nTeco finito ho questo ultimo canto,\nE col mio canto è l'opra tua compita.\n\nOr bianco 'l viso, e l'occhio pien di pianto,\nA te mi volgo, o Padre o Re supremo\nO Creatore o Servatore o Santo.\n\nTutto son tuo. Sola Speranza, io tremo\nE sento 'l cor che batte e sento un gelo\nQuando penso ch'appressa il punto estremo.\n\nDeh m'aita a por giù lo mortal velo,\nE come fia lo spirto uscito fore,\nNol merto no, ma lo raccogli in cielo.\n\nT'amai nel mondo tristo, o sommo Amore,\nInnanzi a tutto, e fu quando peccai,\nColpa di fral non di perverso core.\n\nO Vergin Diva, se prosteso mai\nCaddi in membrarti, a questo mondo basso,\nSe mai ti dissi Madre e se t'amai,\n\nDeh tu soccorri lo spirito lasso\nQuando de l'ore udrà l'ultimo suono,\nDeh tu m'aita ne l'orrendo passo.\n\nO Padre o Redentor, se tuo perdono\nVestirà l'alma, sì ch'io mora e poi\nVenga timido spirto anzi a tuo trono,\n\nE se 'l mondo cangiar co' premi tuoi\nDeggio morendo e con tua santa schiera,\nGiunga 'l sospir di morte, e poi che 'l vuoi,\n\nMi copra un sasso, e mia memoria pera.","id":"canto-v"}]}